LICENSE
MANIFEST.in
README.md
README.txt
requirements.txt
setup.py
singleplatform/__init__.py
singleplatform.egg-info/PKG-INFO
singleplatform.egg-info/SOURCES.txt
singleplatform.egg-info/dependency_links.txt
singleplatform.egg-info/requires.txt
singleplatform.egg-info/top_level.txt
singleplatform.egg-info/zip-safe
singleplatform/tests/__init__.py
singleplatform/tests/_creds.example.py
singleplatform/tests/test_restaurants.py