Metadata-Version: 1.0
Name: singleplatform
Version: 20120430
Summary: easy-as-pie SinglePlatform wrapper library
Home-page: http://github.com/mLewisLogic/singleplatform
Author: Mike Lewis
Author-email: mike@fondu.com
License: MIT License
Download-URL: http://github.com/mLewisLogic/singleplatform/tarball/master
Keywords: singleplatform api
Platform: UNKNOWN
Classifier: Development Status :: 3 - Alpha
Classifier: Intended Audience :: Developers
Classifier: Natural Language :: English
Classifier: Operating System :: OS Independent
Classifier: Programming Language :: Python
Classifier: Topic :: Internet :: WWW/HTTP :: Dynamic Content
Classifier: License :: OSI Approved :: MIT License
